[
	{ 
		"unplanned": [{
							"ppid": 176,
							"nwRound": 39,
							"ogGW": 18,
							"added": false,
							"team_h_nm": "MNC",
							"team_h_id": 13,
							"team_a_id": 4,
							"team_a_nm": "BRE",
							"status": "postponed",
							"reason": "og: 18 Man City plays World Cup of teams."
						}

		] 
	},

	{ 
		"re-planned": [
						 {	
							"ppid": 15,
							"nwRound": 7,
							"ogGW": 2,
							"added": false,
							"team_h_nm": "LUT",
							"team_h_id": 12,
							"team_a_id": 6,
							"team_a_nm": "BUR",
							"status": "replanned",
							"reason": "og = 2: Luton not ready for Home game"
						}
		]
	},

	{ 
		"ppRpIds":[15] 
	},

	{ 
		"ppIds": [176]
	},

	{ 
		"evtp-UIL": 	[
			{	"iBreakId": 1,
				"wkNr": 41,
				"prevGW": 4,
				"prevGWDate": "2023-09-01",
				"nextGW": 5,
				"nextGWDate": "2023-09-16",
				"brkDuration": 2,
				"brkTitle": "IntlBreak 1",
				"passed": 0,
				"toCome": 1
			},
			{	"iBreakId": 2,
				"wkNr": 41,
				"prevGW": 8,
				"prevGWDate": "2023-10-07",
				"nextGW": 9,
				"nextGWDate": "2023-10-21",
				"brkDuration": 2,
				"brkTitle": "IntlBreak 2",
				"passed": 0,
				"toCome": 1
			},
			{	"iBreakId": 3,
				"wkNr": 46,
				"prevGW": 12,
				"prevGWDate": "2023-11-11",
				"nextGW": 13,
				"nextGWDate": "2023-11-25",
				"brkDuration": 1,
				"brkTitle": "IntlBreak 3",
				"passed": 0,
				"toCome": 1
			},
			{	"iBreakId": 4,
				"wkNr": 11,
				"prevGW": 29,
				"prevGWDate": "2024-03-16",
				"nextGW": 30,
				"nextGWDate": "2024-03-30",
				"brkDuration": 2,
				"brkTitle": "IntlBreak 4",
				"passed": 0,
				"toCome": 1
			}
		]
	},

	{
		"evtp-FAC": [
					{ 	"title": "IN", 		"data": [ 1, 2, 3, 4, 5, 6, 7, 8, 9, 10, 11, 12, 13, 14, 15, 16, 17, 18, 19, 20 ]  },
					{	"title": "OUT", 	"data": [ ] },
					{ 	"title": "evntTp", 	"data": "evtp-FAC" },
					{	"title": "FINAL",
						"gw": 38,
						"elim": [ ],
						"drawn": false,
						"data":	[
									{"team_h":0, "team_a":0 }
					 			]
					},
					{	"title": "S-FINAL",
						"gw": 34,
						"elim": [ ],
						"drawn": false,
						"data":	[
									{"team_h":0, "team_a":0 },
									{"team_h":0, "team_a":0 }
						]
					},
					{	"title": "Q-FINAL",
						"gw": 29,
						"elim": [ ],
						"drawn": false,
						"data":	[
									{"team_h":0, "team_a":0 },
									{"team_h":0, "team_a":0 },
									{"team_h":0, "team_a":9 },
									{"team_h":0, "team_a":0 }
						]
					},
					{	"title": "L16 5th Rnd. Feb 28",
						"gw": 26,
						"elim": [ ],
						"drawn": false,
						"data":	[
									{"team_h":0, 	"team_a":0 },
									{"team_h":0, 	"team_a":0 },
									{"team_h":0, 	"team_a":0 },
									{"team_h":0, 	"team_a":0 },
									{"team_h":0, 	"team_a":0 },
									{"team_h":0, 	"team_a":0 },
									{"team_h":0, 	"team_a":0 },
									{"team_h":0, 	"team_a":0 },
									{"team_h":0, 	"team_a":0 },
									{"team_h":0, 	"team_a":0 },
									{"team_h":0, 	"team_a":0 },
									{"team_h":0, 	"team_a":0 },
									{"team_h":0, 	"team_a":0 },
									{"team_h":0, 	"team_a":0 },
									{"team_h":0, 	"team_a":0 },
									{"team_h":0, 	"team_a":0 }
						]
					},
					{	"title": "L32 4th Rnd. Jan 27",
						"gw": 21,
						"elim": [ ],
						"drawn": false,
						"data":	[
									{"team_h":0, 	"team_a":0 },
									{"team_h":0, 	"team_a":0 },
									{"team_h":0, 	"team_a":0 },
									{"team_h":0, 	"team_a":0 },
									{"team_h":0, 	"team_a":0 },
									{"team_h":0, 	"team_a":0 },
									{"team_h":0, 	"team_a":0 },
									{"team_h":0, 	"team_a":0 },
									{"team_h":0, 	"team_a":0 },
									{"team_h":0, 	"team_a":0 },
									{"team_h":0, 	"team_a":0 },
									{"team_h":0, 	"team_a":0 },
									{"team_h":0, 	"team_a":0 },
									{"team_h":0, 	"team_a":0 },
									{"team_h":0, 	"team_a":0 },
									{"team_h":0, 	"team_a":0 }
						]
					},
					{	"title": "L64 3rd Rnd. Jan. 6",
						"gw": 20,
						"elim": [],
						"drawn": false,
						"data": [
									{"team_h":1,  "team_a":0,  	"oppNmA":"Exempt" },
									{"team_h":2,  "team_a":0,  	"oppNmA":"Exempt" },
									{"team_h":0,  "team_a":0,  	"oppNmA":"Exempt" },
									{"team_h":4,  "team_a":0,  	"oppNmA":"Exempt" },
									{"team_h":5,  "team_a":0,  	"oppNmA":"Exempt" },
									{"team_h":6,  "team_a":0,  	"oppNmA":"Exempt" },
									{"team_h":7,  "team_a":0,  	"oppNmA":"Exempt" },
									{"team_h":8,  "team_a":0,  	"oppNmA":"Exempt" },
									{"team_h":9,  "team_a":0,  	"oppNmA":"Exempt" },
									{"team_h":10,  "team_a":0,  "oppNmA":"Exempt" },
									{"team_h":11,  "team_a":0,  "oppNmA":"Exempt" },
									{"team_h":12,  "team_a":0,  "oppNmA":"Exempt" },
									{"team_h":13,  "team_a":0,  "oppNmA":"Exempt" },
									{"team_h":14,  "team_a":0,  "oppNmA":"Exempt" },
									{"team_h":15,  "team_a":0,  "oppNmA":"Exempt" },
									{"team_h":16,  "team_a":0,  "oppNmA":"Exempt" },
									{"team_h":17,  "team_a":0,  "oppNmA":"Exempt" },
									{"team_h":18,  "team_a":0,  "oppNmA":"Exempt" },
									{"team_h":19,  "team_a":0,  "oppNmA":"Exempt" },
									{"team_h":20,  "team_a":0,  "oppNmA":"Exempt" }
						]
					}
		]
	},

	{
		"evtp-EFL":[
					{ 	"title": "IN", 		"data": [  7, 9, 10, 11, 15, 19 ] },
					{	"title": "OUT", 	"data": [  1, 2, 3, 4, 5, 6, 8, 12, 13, 14, 16, 17, 18, 20 ] },
					{ 	"title": "evntTp", 	"data": "evtp-EFL" },
					{ 	"title": "FINAL",	
						"gw": 26,
						"elim": [ 1, 2, 3, 4, 5, 6, 8, 12, 13, 14, 16, 17, 18, 20 ],
						"drawn": false,
						"data": [ 	
									{"team_h":0, "team_a":0 } 
								] 
					},
					{ 	"title": "S-FINAL returns",
						"gw": 21,
						"elim": [ 1, 2, 3, 4, 5, 6, 8, 12, 13, 14, 16, 17, 18, 20 ],
						"drawn": false,
						"data": [ 
									{"team_h":0, "team_a":0},
									{"team_h":0, "team_a":0}
						]
					},
					{ 	"title": "S-FINAL first",
						"gw": 20,
						"elim": [ 1, 2, 3, 4, 5, 6, 8, 12, 13, 14, 16, 17, 18, 20 ],
						"drawn": false,
						"data": [ 
									{"team_h":0, "team_a":0 },
									{"team_h":0, "team_a":0 }
						]
					},
					{ 	"title": "Q-FINAL",
						"gw": 17,
						"elim": [ 1, 2, 3, 4, 5, 6, 8, 12, 13, 14, 16, 17, 18, 20 ],
						"drawn": true,
						"data": [ 
									{"team_h": 9, "team_a":10 },
									{"team_h": 7, "team_a":15 },
									{"team_h":11, "team_a":19 }
					 	]
					},
					{ 	"title": "L16",
						"gw": 10,
						"elim": [ 2, 4, 5, 8, 12, 13, 16, 17 ,18, 20 ],
						"drawn": true,
						"data": [ 
									{"team_h":14, "team_a":15 	},
									{"team_h":3, "team_a":11	},
									{"team_h":7, "team_a":0, 	"oppNmA":"Blackburn Rovers" },
									{"team_h":9, "team_a":6 	},
									{"team_h":0, "team_a":10, 	"oppNmH":"Ipswitch" },
									{"team_h":19, "team_a":1	}
						]
					},
					{ 	"title": "L32",
						"gw": 6,
						"elim": [ 16, 17 ,18 ],
						"drawn": true,
						"data": [ 
									{"team_h": 4, "team_a": 1 	},
									{"team_h": 2, "team_a": 9 	},
									{"team_h": 3, "team_a": 0, 	"oppNmA":"Stoke" },
									{"team_h": 7, "team_a": 5 	},
									{"team_h": 0, "team_a":12, 	"oppNmH":"Exeter" },
									{"team_h":10, "team_a": 0, 	"oppNmA":"Norwich" },
									{"team_h": 0, "team_a":20,	"oppNmH":"Ipswich" },
									{"team_h": 0, "team_a":19,	"oppNmH":"Lincoln" },
									{"team_h":11, "team_a": 0, 	"oppNmA":"Leicester" },
									{"team_h":14, "team_a": 8 	},
									{"team_h":15, "team_a":13	},
									{"team_h": 0, "team_a": 6, 	"oppNmH":"Salford" }
					 	]
					},
					{ 	"title": "L64",
						"gw": 3,
						"elim": [ ],
						"drawn": true,
						"data": [ 
									{"team_h": 1, "team_a": 0,	"oppNmA":"Exempt" 	},
									{"team_h": 2, "team_a": 0,	"oppNmA":"Hibs" 	},
									{"team_h": 0, "team_a": 3,	"oppNmH":"Swansea" 	},
									{"team_h": 0, "team_a": 4,	"oppNmH":"Newport" 	},
									{"team_h": 5, "team_a": 0,	"oppNmA":"Exempt" 	},
									{"team_h":16, "team_a": 6	},
									{"team_h": 7, "team_a": 0,	"oppNmA":"Wimbledon"},
									{"team_h": 0, "team_a": 8,	"oppNmH":"Plymouth Arguile" },
									{"team_h": 0, "team_a": 9,	"oppNmH":"Doncaster" },
									{"team_h":10, "team_a":18	},
									{"team_h":11, "team_a": 0,	"oppNmA":"Exempt" 	},
									{"team_h":12, "team_a": 0,	"oppNmA":"Gillingham"},
									{"team_h":13, "team_a": 0,	"oppNmA":"Exempt" 	},
									{"team_h":14, "team_a": 0,	"oppNmA":"Exempt" 	},
									{"team_h":15, "team_a": 0,	"oppNmA":"Exempt" 	},
									{"team_h":17, "team_a": 0,	"oppNmA":"Lincoln City" },
									{"team_h":19, "team_a": 0,	"oppNmA":"Exempt" 	},
									{"team_h":20, "team_a": 0,	"oppNmA":"Blackpool"}
					 	]
					}				
		]
	},

	{	"example": {	
			"ppid": 319,
			"nwRound": 37,
			"ogGW": 32,
			"added": false,
			"team_h_nm": "MNU",
			"team_h_id": 14,
			"team_a_id": 6,
			"team_a_nm": "CHE",
			"status": "postponed",
			"reason": "og: 32: FA Cup SEMI Final for MNU and CHE"
		}
	}
]


